good_agent/__init__.py
good_agent/agent/__init__.py
good_agent/agent/components.py
good_agent/agent/config/__init__.py
good_agent/agent/config/context.py
good_agent/agent/config/manager.py
good_agent/agent/config/types.py
good_agent/agent/context.py
good_agent/agent/conversation.py
good_agent/agent/core.py
good_agent/agent/llm.py
good_agent/agent/messages.py
good_agent/agent/modes.py
good_agent/agent/pool.py
good_agent/agent/state.py
good_agent/agent/system_prompt.py
good_agent/agent/tasks.py
good_agent/agent/thread_context.py
good_agent/agent/tools.py
good_agent/agent/versioning.py
good_agent/agents/__init__.py
good_agent/agents/meta.py
good_agent/agents/research.py
good_agent/cli/config.py
good_agent/cli/main.py
good_agent/cli/prompts.py
good_agent/cli/run.py
good_agent/cli/serve.py
good_agent/cli/utils.py
good_agent/content/__init__.py
good_agent/content/parts.py
good_agent/core/__init__.py
good_agent/core/components/AGENTS.md
good_agent/core/components/TOOL_ADAPTER.md
good_agent/core/components/__init__.py
good_agent/core/components/component.py
good_agent/core/components/injection.py
good_agent/core/components/tool_adapter.py
good_agent/core/event_router/__init__.py
good_agent/core/event_router/advanced.py
good_agent/core/event_router/context.py
good_agent/core/event_router/core.py
good_agent/core/event_router/decorators.py
good_agent/core/event_router/protocols.py
good_agent/core/event_router/registration.py
good_agent/core/event_router/sync_bridge.py
good_agent/core/indexing.py
good_agent/core/markdown.py
good_agent/core/mdxl.py
good_agent/core/models/__init__.py
good_agent/core/models/application.py
good_agent/core/models/base.py
good_agent/core/models/mixins.py
good_agent/core/models/protocols.py
good_agent/core/models/reference.py
good_agent/core/models/renderable.py
good_agent/core/models/serializers.py
good_agent/core/param_naming.py
good_agent/core/signal_handler.py
good_agent/core/templates.py
good_agent/core/templating/README.md
good_agent-0.6.2.dist-info/WHEEL
good_agent-0.6.2.dist-info/entry_points.txt
good_agent-0.6.2.dist-info/METADATA
good_agent-0.6.2.dist-info/RECORD
