Metadata-Version: 2.3
Name: good-agent
Version: 0.6.2
Summary: A Good Agent
Author: Chris Goddard
Author-email: Chris Goddard <chris@goodkiwi.llc>
Requires-Dist: good-common>=1.2.1
Requires-Dist: instructor>=1.12.0
Requires-Dist: jinja2>=3.1.6
Requires-Dist: lxml-html-clean>=0.4.3
Requires-Dist: markdown>=3.9
Requires-Dist: litellm
Requires-Dist: mcp>=1.0.0
Requires-Dist: rich>=13.7.0
Requires-Dist: numpy>=2.3.4
Requires-Dist: pydantic>=2.12.3
Requires-Dist: python-magic>=0.4.27
Requires-Dist: types-lxml>=2025.8.25
Requires-Dist: prompt-toolkit>=3.0.52
Requires-Dist: tomli-w>=1.0.0
Requires-Python: >=3.14
